initial_implementation/AlternativeFunctions.py
initial_implementation/DRexParam.py
initial_implementation/PyDRex.py
initial_implementation/PyDRexFullIVP.py
initial_implementation/README.md
initial_implementation/pbs_cluster_instructions/job.sh
initial_implementation/pbs_cluster_instructions/startWorkerNode.sh
initial_implementation/visualisation/PlotDRex.py
initial_implementation/visualisation/pathlineIVP.py
pydrex/__init__.py
pydrex/axes.py
pydrex/cli.py
pydrex/core.py
pydrex/diagnostics.py
pydrex/distributed.py
pydrex/exceptions.py
pydrex/geometry.py
pydrex/io.py
pydrex/logger.py
pydrex/mesh.py
pydrex/minerals.py
pydrex/mock.py
pydrex/pathlines.py
pydrex/stats.py
pydrex/tensors.py
pydrex/utils.py
pydrex/velocity.py
pydrex/visualisation.py
pydrex/data/drexF90/olA_D1E4_dt50_X0_L5.scsv
pydrex/data/outputs/example_CPO_poles_001xy.npz
pydrex/data/outputs/example_CPO_poles_001xz.npz
pydrex/data/outputs/example_CPO_poles_001yz.npz
pydrex/data/outputs/example_CPO_poles_010xy.npz
pydrex/data/outputs/example_CPO_poles_010xz.npz
pydrex/data/outputs/example_CPO_poles_010yz.npz
pydrex/data/outputs/example_CPO_poles_100xy.npz
pydrex/data/outputs/example_CPO_poles_100xz.npz
pydrex/data/outputs/example_CPO_poles_100yz.npz
pydrex/data/outputs/example_CPO_resampled.npz
pydrex/data/rng/hexaxis_nearX45_seeds.scsv
pydrex/data/rng/seeds.scsv
pydrex/data/specs/spec.scsv
pydrex/data/specs/spec.toml
pydrex/data/specs/start.scsv
pydrex/data/steadyflow/corner2d_2cmyr_5e5x1e5.vtu
pydrex/data/thirdparty/Kaminski2001_GBMshear.scsv
pydrex/data/thirdparty/Kaminski2002_ISAtime.scsv
pydrex/data/thirdparty/Kaminski2004_AaxisDynamicShear.scsv
pydrex/data/thirdparty/Kaminski2004_GBSshear.scsv
pydrex/data/thirdparty/Skemer2016_ShearStrainAngles.scsv
pydrex/data/thirdparty/a_axis_GBS_fortran.scsv
pydrex/data/thirdparty/a_axis_GBS_long_fortran.scsv
pydrex-0.0.1.dist-info/LICENSE
pydrex-0.0.1.dist-info/METADATA
pydrex-0.0.1.dist-info/WHEEL
pydrex-0.0.1.dist-info/entry_points.txt
pydrex-0.0.1.dist-info/top_level.txt
pydrex-0.0.1.dist-info/RECORD
