Metadata-Version: 2.1
Name: pydrex
Version: 0.0.1
Summary: Dynamic CPO calculations for olivine-enstatite polycrystal aggregates
Author: Chris Mathews
Author-email: Thomas Duvernay <td75013@hotmail.fr>, Leon Bilton <adigitoleo@posteo.net>
License: GNU GENERAL PUBLIC LICENSE
Project-URL: repository, https://github.com/seismic-anisotropy/PyDRex
Project-URL: documentation, https://seismic-anisotropy.github.io/PyDRex/
Keywords: CPO,LPO,olivine,deformation,anisotropy,crystallography
Classifier: Programming Language :: Python :: 3
Classifier: Development Status :: 2 - Pre-Alpha
Classifier: Topic :: Scientific/Engineering :: Physics
Classifier: Intended Audience :: Developers
Classifier: Intended Audience :: Science/Research
Requires-Python: >=3.10
License-File: LICENSE
Requires-Dist: numpy >=1.8
Requires-Dist: numba >=0.57
Requires-Dist: scipy >=1.2
Requires-Dist: pyyaml
Requires-Dist: meshio
Requires-Dist: matplotlib
Requires-Dist: cmcrameri
Requires-Dist: h5py
Requires-Dist: tqdm
Requires-Dist: tomli >=1.1.0 ; python_version < "3.11"
Provides-Extra: dev
Requires-Dist: pytest ; extra == 'dev'
Requires-Dist: uniplot ; extra == 'dev'
Requires-Dist: pdoc ; extra == 'dev'
Requires-Dist: ruff ; extra == 'dev'
Requires-Dist: black ; extra == 'dev'
Requires-Dist: isort ; extra == 'dev'
Requires-Dist: ptpython ; extra == 'dev'
Provides-Extra: doc
Requires-Dist: pdoc ; extra == 'doc'
Provides-Extra: lsp
Requires-Dist: python-lsp-server ; extra == 'lsp'
Requires-Dist: pyls-isort ; extra == 'lsp'
Requires-Dist: python-lsp-black ; extra == 'lsp'
Requires-Dist: python-lsp-ruff ; extra == 'lsp'
Provides-Extra: mesh
Requires-Dist: gmsh ; extra == 'mesh'
Provides-Extra: ray
Requires-Dist: ray >=2.0.0 ; extra == 'ray'
Provides-Extra: test
Requires-Dist: pytest ; extra == 'test'
